[
  {
    "trend_arrow": "FLAT", 
    "display_time": "2016-07-01T20:34:32-07:00", 
    "noise": 1, 
    "system_time": "2016-07-02T03:26:12-07:00", 
    "direction": "Flat", 
    "sgv": 260, 
    "dateString": "2016-07-01T20:34:32-07:00", 
    "device": "openaps://cgm", 
    "unfiltered": 281280, 
    "rssi": 198, 
    "date": 1467430472000, 
    "filtered": 273792, 
    "type": "sgv", 
    "glucose": 260
  }, 
  {
    "trend_arrow": "FLAT", 
    "display_time": "2016-07-01T20:34:32-07:00", 
    "noise": 1, 
    "system_time": "2016-07-02T03:26:12-07:00", 
    "direction": "Flat", 
    "sgv": 261, 
    "dateString": "2016-07-01T20:34:32-07:00", 
    "device": "openaps://cgm", 
    "unfiltered": 278656, 
    "rssi": 190, 
    "date": 1467430472000, 
    "filtered": 277184, 
    "type": "sgv", 
    "glucose": 261
  }, 
  {
    "trend_arrow": "FLAT", 
    "display_time": "2016-07-01T20:29:30-07:00", 
    "noise": 1, 
    "system_time": "2016-07-02T03:21:10-07:00", 
    "direction": "Flat", 
    "sgv": 245, 
    "dateString": "2016-07-01T20:29:30-07:00", 
    "device": "openaps://cgm", 
    "unfiltered": 275456, 
    "rssi": 183, 
    "date": 1467430170000, 
    "filtered": 286208, 
    "type": "sgv", 
    "glucose": 245
  }, 
  {
    "trend_arrow": "FLAT", 
    "display_time": "2016-07-01T20:54:31-07:00", 
    "noise": 1, 
    "system_time": "2016-07-02T03:46:10-07:00", 
    "direction": "Flat", 
    "sgv": 282, 
    "dateString": "2016-07-01T20:54:31-07:00", 
    "device": "openaps://cgm", 
    "unfiltered": 301632, 
    "rssi": 436, 
    "date": 1467431671000, 
    "filtered": 295488, 
    "type": "sgv", 
    "glucose": 282
  }, 
  {
    "trend_arrow": "FLAT", 
    "display_time": "2016-07-01T20:49:30-07:00", 
    "noise": 1, 
    "system_time": "2016-07-02T03:41:10-07:00", 
    "direction": "Flat", 
    "sgv": 275, 
    "dateString": "2016-07-01T20:49:30-07:00", 
    "device": "openaps://cgm", 
    "unfiltered": 294720, 
    "rssi": 196, 
    "date": 1467431370000, 
    "filtered": 290816, 
    "type": "sgv", 
    "glucose": 275
  }, 
  {
    "trend_arrow": "45_DOWN", 
    "display_time": "2016-07-01T21:14:31-07:00", 
    "noise": 1, 
    "system_time": "2016-07-02T04:06:10-07:00", 
    "direction": "FortyFiveDown", 
    "sgv": 267, 
    "dateString": "2016-07-01T21:14:31-07:00", 
    "device": "openaps://cgm", 
    "unfiltered": 287680, 
    "rssi": 444, 
    "date": 1467432871000, 
    "filtered": 301504, 
    "type": "sgv", 
    "glucose": 267
  }, 
  {
    "trend_arrow": "FLAT", 
    "display_time": "2016-07-01T21:09:30-07:00", 
    "noise": 1, 
    "system_time": "2016-07-02T04:01:10-07:00", 
    "direction": "Flat", 
    "sgv": 276, 
    "dateString": "2016-07-01T21:09:30-07:00", 
    "device": "openaps://cgm", 
    "unfiltered": 295680, 
    "rssi": 200, 
    "date": 1467432570000, 
    "filtered": 303808, 
    "type": "sgv", 
    "glucose": 276
  }, 
  {
    "trend_arrow": "45_DOWN", 
    "display_time": "2016-07-01T21:39:31-07:00", 
    "noise": 1, 
    "system_time": "2016-07-02T04:31:10-07:00", 
    "direction": "FortyFiveDown", 
    "sgv": 236, 
    "dateString": "2016-07-01T21:39:31-07:00", 
    "device": "openaps://cgm", 
    "unfiltered": 259904, 
    "rssi": 423, 
    "date": 1467434371000, 
    "filtered": 264192, 
    "type": "sgv", 
    "glucose": 236
  }, 
  {
    "trend_arrow": "45_DOWN", 
    "display_time": "2016-07-01T21:34:30-07:00", 
    "noise": 1, 
    "system_time": "2016-07-02T04:26:10-07:00", 
    "direction": "FortyFiveDown", 
    "sgv": 234, 
    "dateString": "2016-07-01T21:34:30-07:00", 
    "device": "openaps://cgm", 
    "unfiltered": 258368, 
    "rssi": 194, 
    "date": 1467434070000, 
    "filtered": 270784, 
    "type": "sgv", 
    "glucose": 234
  }, 
  {
    "trend_arrow": "NOT_COMPUTABLE", 
    "display_time": "2016-07-01T22:09:31-07:00", 
    "noise": 4, 
    "system_time": "2016-07-02T05:01:10-07:00", 
    "direction": "NOT COMPUTABLE", 
    "sgv": 10, 
    "dateString": "2016-07-01T22:09:31-07:00", 
    "device": "openaps://cgm", 
    "unfiltered": 176896, 
    "rssi": 444, 
    "date": 1467436171000, 
    "filtered": 211936, 
    "type": "sgv", 
    "glucose": 10
  }, 
  {
    "trend_arrow": "NOT_COMPUTABLE", 
    "display_time": "2016-07-01T22:04:30-07:00", 
    "noise": 4, 
    "system_time": "2016-07-02T04:56:10-07:00", 
    "direction": "NOT COMPUTABLE", 
    "sgv": 10, 
    "dateString": "2016-07-01T22:04:30-07:00", 
    "device": "openaps://cgm", 
    "unfiltered": 188288, 
    "rssi": 205, 
    "date": 1467435870000, 
    "filtered": 215808, 
    "type": "sgv", 
    "glucose": 10
  }, 
  {
    "trend_arrow": "FLAT", 
    "display_time": "2016-07-02T00:49:30-07:00", 
    "noise": 1, 
    "system_time": "2016-07-02T07:41:09-07:00", 
    "direction": "Flat", 
    "sgv": 114, 
    "dateString": "2016-07-02T00:49:30-07:00", 
    "device": "openaps://cgm", 
    "unfiltered": 149696, 
    "rssi": 221, 
    "date": 1467445770000, 
    "filtered": 140864, 
    "type": "sgv", 
    "glucose": 114
  }, 
  {
    "trend_arrow": "FLAT", 
    "display_time": "2016-07-02T00:44:30-07:00", 
    "noise": 1, 
    "system_time": "2016-07-02T07:36:09-07:00", 
    "direction": "Flat", 
    "sgv": 105, 
    "dateString": "2016-07-02T00:44:30-07:00", 
    "device": "openaps://cgm", 
    "unfiltered": 141664, 
    "rssi": 221, 
    "date": 1467445470000, 
    "filtered": 139008, 
    "type": "sgv", 
    "glucose": 105
  }
]