[
  {
    "trend_arrow": "FLAT", 
    "display_time": "2016-07-05T15:51:58-07:00", 
    "noise": 1, 
    "system_time": "2016-07-05T21:48:43-07:00", 
    "direction": "Flat", 
    "sgv": 154, 
    "dateString": "2016-07-05T15:51:58-07:00", 
    "device": "openaps://cgm", 
    "unfiltered": 155840, 
    "rssi": 695, 
    "date": 1467759118000, 
    "filtered": 151328, 
    "type": "sgv", 
    "glucose": 154
  }, 
  {
    "trend_arrow": "FLAT", 
    "display_time": "2016-07-05T15:46:57-07:00", 
    "noise": 1, 
    "system_time": "2016-07-05T21:43:42-07:00", 
    "direction": "Flat", 
    "sgv": 148, 
    "dateString": "2016-07-05T15:46:57-07:00", 
    "device": "openaps://cgm", 
    "unfiltered": 151616, 
    "rssi": 186, 
    "date": 1467758817000, 
    "filtered": 149216, 
    "type": "sgv", 
    "glucose": 148
  }, 
  {
    "trend_arrow": "45_UP", 
    "display_time": "2016-07-05T17:46:57-07:00", 
    "noise": 1, 
    "system_time": "2016-07-05T23:43:42-07:00", 
    "direction": "FortyFiveUp", 
    "sgv": 98, 
    "dateString": "2016-07-05T17:46:57-07:00", 
    "device": "openaps://cgm", 
    "unfiltered": 114864, 
    "rssi": 197, 
    "date": 1467766017000, 
    "filtered": 103376, 
    "type": "sgv", 
    "glucose": 98
  }, 
  {
    "trend_arrow": "FLAT", 
    "display_time": "2016-07-05T17:41:56-07:00", 
    "noise": 1, 
    "system_time": "2016-07-05T23:38:42-07:00", 
    "direction": "Flat", 
    "sgv": 87, 
    "dateString": "2016-07-05T17:41:56-07:00", 
    "device": "openaps://cgm", 
    "unfiltered": 106800, 
    "rssi": 180, 
    "date": 1467765716000, 
    "filtered": 99104, 
    "type": "sgv", 
    "glucose": 87
  }, 
  {
    "trend_arrow": "FLAT", 
    "display_time": "2016-07-05T18:36:57-07:00", 
    "noise": 1, 
    "system_time": "2016-07-06T00:33:42-07:00", 
    "direction": "Flat", 
    "sgv": 163, 
    "dateString": "2016-07-05T18:36:57-07:00", 
    "device": "openaps://cgm", 
    "unfiltered": 163104, 
    "rssi": 436, 
    "date": 1467769017000, 
    "filtered": 161568, 
    "type": "sgv", 
    "glucose": 163
  }, 
  {
    "trend_arrow": "FLAT", 
    "display_time": "2016-07-05T18:31:56-07:00", 
    "noise": 1, 
    "system_time": "2016-07-06T00:28:42-07:00", 
    "direction": "Flat", 
    "sgv": 162, 
    "dateString": "2016-07-05T18:31:56-07:00", 
    "device": "openaps://cgm", 
    "unfiltered": 162304, 
    "rssi": 188, 
    "date": 1467768716000, 
    "filtered": 158912, 
    "type": "sgv", 
    "glucose": 162
  }, 
  {
    "trend_arrow": "FLAT", 
    "display_time": "2016-07-05T18:51:57-07:00", 
    "noise": 1, 
    "system_time": "2016-07-06T00:48:42-07:00", 
    "direction": "Flat", 
    "sgv": 153, 
    "dateString": "2016-07-05T18:51:57-07:00", 
    "device": "openaps://cgm", 
    "unfiltered": 155712, 
    "rssi": 450, 
    "date": 1467769917000, 
    "filtered": 161472, 
    "type": "sgv", 
    "glucose": 153
  }, 
  {
    "trend_arrow": "FLAT", 
    "display_time": "2016-07-05T18:46:56-07:00", 
    "noise": 1, 
    "system_time": "2016-07-06T00:43:42-07:00", 
    "direction": "Flat", 
    "sgv": 158, 
    "dateString": "2016-07-05T18:46:56-07:00", 
    "device": "openaps://cgm", 
    "unfiltered": 159200, 
    "rssi": 179, 
    "date": 1467769616000, 
    "filtered": 163200, 
    "type": "sgv", 
    "glucose": 158
  }, 
  {
    "trend_arrow": "SINGLE_DOWN", 
    "display_time": "2016-07-05T19:11:57-07:00", 
    "noise": 1, 
    "system_time": "2016-07-06T01:08:42-07:00", 
    "direction": "SingleDown", 
    "sgv": 101, 
    "dateString": "2016-07-05T19:11:57-07:00", 
    "device": "openaps://cgm", 
    "unfiltered": 117376, 
    "rssi": 432, 
    "date": 1467771117000, 
    "filtered": 135456, 
    "type": "sgv", 
    "glucose": 101
  }, 
  {
    "trend_arrow": "SINGLE_DOWN", 
    "display_time": "2016-07-05T19:06:56-07:00", 
    "noise": 1, 
    "system_time": "2016-07-06T01:03:42-07:00", 
    "direction": "SingleDown", 
    "sgv": 115, 
    "dateString": "2016-07-05T19:06:56-07:00", 
    "device": "openaps://cgm", 
    "unfiltered": 127824, 
    "rssi": 180, 
    "date": 1467770816000, 
    "filtered": 145408, 
    "type": "sgv", 
    "glucose": 115
  }, 
  {
    "trend_arrow": "FLAT", 
    "display_time": "2016-07-05T19:51:56-07:00", 
    "noise": 1, 
    "system_time": "2016-07-06T01:48:42-07:00", 
    "direction": "Flat", 
    "sgv": 71, 
    "dateString": "2016-07-05T19:51:56-07:00", 
    "device": "openaps://cgm", 
    "unfiltered": 95408, 
    "rssi": 198, 
    "date": 1467773516000, 
    "filtered": 85648, 
    "type": "sgv", 
    "glucose": 71
  }, 
  {
    "trend_arrow": "FLAT", 
    "display_time": "2016-07-05T19:46:56-07:00", 
    "noise": 1, 
    "system_time": "2016-07-06T01:43:41-07:00", 
    "direction": "Flat", 
    "sgv": 61, 
    "dateString": "2016-07-05T19:46:56-07:00", 
    "device": "openaps://cgm", 
    "unfiltered": 87584, 
    "rssi": 188, 
    "date": 1467773216000, 
    "filtered": 84976, 
    "type": "sgv", 
    "glucose": 61
  }
]