[
  {
    "trend_arrow": "FLAT", 
    "display_time": "2016-06-25T22:35:18-07:00", 
    "noise": 1, 
    "system_time": "2016-06-26T04:32:03-07:00", 
    "direction": "Flat", 
    "sgv": 133, 
    "dateString": "2016-06-25T22:35:18-07:00", 
    "device": "openaps://cgm", 
    "unfiltered": 159456, 
    "rssi": 197, 
    "date": 1466919318000, 
    "filtered": 154464, 
    "type": "sgv", 
    "glucose": 133
  }, 
  {
    "trend_arrow": "FLAT", 
    "display_time": "2016-06-25T22:30:17-07:00", 
    "noise": 1, 
    "system_time": "2016-06-26T04:27:03-07:00", 
    "direction": "Flat", 
    "sgv": 129, 
    "dateString": "2016-06-25T22:30:17-07:00", 
    "device": "openaps://cgm", 
    "unfiltered": 155648, 
    "rssi": 179, 
    "date": 1466919017000, 
    "filtered": 153536, 
    "type": "sgv", 
    "glucose": 129
  }, 
  {
    "trend_arrow": "FLAT", 
    "display_time": "2016-06-25T22:55:18-07:00", 
    "noise": 1, 
    "system_time": "2016-06-26T04:52:03-07:00", 
    "direction": "Flat", 
    "sgv": 126, 
    "dateString": "2016-06-25T22:55:18-07:00", 
    "device": "openaps://cgm", 
    "unfiltered": 152128, 
    "rssi": 440, 
    "date": 1466920518000, 
    "filtered": 156800, 
    "type": "sgv", 
    "glucose": 126
  }, 
  {
    "trend_arrow": "FLAT", 
    "display_time": "2016-06-25T22:50:17-07:00", 
    "noise": 1, 
    "system_time": "2016-06-26T04:47:03-07:00", 
    "direction": "Flat", 
    "sgv": 126, 
    "dateString": "2016-06-25T22:50:17-07:00", 
    "device": "openaps://cgm", 
    "unfiltered": 152512, 
    "rssi": 204, 
    "date": 1466920217000, 
    "filtered": 158784, 
    "type": "sgv", 
    "glucose": 126
  }, 
  {
    "trend_arrow": "FLAT", 
    "display_time": "2016-06-25T23:05:18-07:00", 
    "noise": 1, 
    "system_time": "2016-06-26T05:02:03-07:00", 
    "direction": "Flat", 
    "sgv": 135, 
    "dateString": "2016-06-25T23:05:18-07:00", 
    "device": "openaps://cgm", 
    "unfiltered": 161056, 
    "rssi": 459, 
    "date": 1466921118000, 
    "filtered": 153056, 
    "type": "sgv", 
    "glucose": 135
  }, 
  {
    "trend_arrow": "FLAT", 
    "display_time": "2016-06-25T23:00:17-07:00", 
    "noise": 1, 
    "system_time": "2016-06-26T04:57:03-07:00", 
    "direction": "Flat", 
    "sgv": 128, 
    "dateString": "2016-06-25T23:00:17-07:00", 
    "device": "openaps://cgm", 
    "unfiltered": 154176, 
    "rssi": 207, 
    "date": 1466920817000, 
    "filtered": 153920, 
    "type": "sgv", 
    "glucose": 128
  }, 
  {
    "trend_arrow": "FLAT", 
    "display_time": "2016-06-26T01:40:17-07:00", 
    "noise": 1, 
    "system_time": "2016-06-26T07:37:02-07:00", 
    "direction": "Flat", 
    "sgv": 159, 
    "dateString": "2016-06-26T01:40:17-07:00", 
    "device": "openaps://cgm", 
    "unfiltered": 185824, 
    "rssi": 199, 
    "date": 1466930417000, 
    "filtered": 186528, 
    "type": "sgv", 
    "glucose": 159
  }, 
  {
    "trend_arrow": "FLAT", 
    "display_time": "2016-06-26T01:35:17-07:00", 
    "noise": 1, 
    "system_time": "2016-06-26T07:32:02-07:00", 
    "direction": "Flat", 
    "sgv": 160, 
    "dateString": "2016-06-26T01:35:17-07:00", 
    "device": "openaps://cgm", 
    "unfiltered": 186400, 
    "rssi": 185, 
    "date": 1466930117000, 
    "filtered": 183520, 
    "type": "sgv", 
    "glucose": 160
  }
]