[
  {
    "trend_arrow": "FLAT", 
    "display_time": "2016-07-15T23:06:08-07:00", 
    "noise": 1, 
    "system_time": "2016-07-16T05:57:23-07:00", 
    "direction": "Flat", 
    "sgv": 76, 
    "dateString": "2016-07-15T23:06:08-07:00", 
    "device": "openaps://cgm", 
    "unfiltered": 82288, 
    "rssi": 445, 
    "date": 1468649168000, 
    "filtered": 86752, 
    "type": "sgv", 
    "glucose": 76
  }, 
  {
    "trend_arrow": "45_DOWN", 
    "display_time": "2016-07-15T23:01:07-07:00", 
    "noise": 1, 
    "system_time": "2016-07-16T05:52:23-07:00", 
    "direction": "FortyFiveDown", 
    "sgv": 76, 
    "dateString": "2016-07-15T23:01:07-07:00", 
    "device": "openaps://cgm", 
    "unfiltered": 82704, 
    "rssi": 196, 
    "date": 1468648867000, 
    "filtered": 93888, 
    "type": "sgv", 
    "glucose": 76
  }, 
  {
    "trend_arrow": "FLAT", 
    "display_time": "2016-07-16T03:11:06-07:00", 
    "noise": 1, 
    "system_time": "2016-07-16T10:02:22-07:00", 
    "direction": "Flat", 
    "sgv": 107, 
    "dateString": "2016-07-16T03:11:06-07:00", 
    "device": "openaps://cgm", 
    "unfiltered": 109552, 
    "rssi": 184, 
    "date": 1468663866000, 
    "filtered": 103728, 
    "type": "sgv", 
    "glucose": 107
  }, 
  {
    "trend_arrow": "FLAT", 
    "display_time": "2016-07-16T03:06:06-07:00", 
    "noise": 1, 
    "system_time": "2016-07-16T09:57:22-07:00", 
    "direction": "Flat", 
    "sgv": 106, 
    "dateString": "2016-07-16T03:06:06-07:00", 
    "device": "openaps://cgm", 
    "unfiltered": 108512, 
    "rssi": 186, 
    "date": 1468663566000, 
    "filtered": 101120, 
    "type": "sgv", 
    "glucose": 106
  }
]