[
  {
    "trend_arrow": "FLAT", 
    "display_time": "2016-07-14T19:36:14-07:00", 
    "noise": 1, 
    "system_time": "2016-07-15T02:27:29-07:00", 
    "direction": "Flat", 
    "sgv": 89, 
    "dateString": "2016-07-14T19:36:14-07:00", 
    "date": 1468550174000, 
    "unfiltered": 97904, 
    "filtered": 102576, 
    "device": "openaps://cgm", 
    "rssi": 442, 
    "type": "sgv", 
    "glucose": 89
  }, 
  {
    "trend_arrow": "FLAT", 
    "display_time": "2016-07-14T19:31:13-07:00", 
    "noise": 1, 
    "system_time": "2016-07-15T02:22:29-07:00", 
    "direction": "Flat", 
    "sgv": 92, 
    "dateString": "2016-07-14T19:31:13-07:00", 
    "date": 1468549873000, 
    "unfiltered": 100096, 
    "filtered": 106624, 
    "device": "openaps://cgm", 
    "rssi": 184, 
    "type": "sgv", 
    "glucose": 92
  }, 
  {
    "trend_arrow": "FLAT", 
    "display_time": "2016-07-14T21:26:13-07:00", 
    "noise": 1, 
    "system_time": "2016-07-15T04:17:28-07:00", 
    "direction": "Flat", 
    "sgv": 112, 
    "dateString": "2016-07-14T21:26:13-07:00", 
    "date": 1468556773000, 
    "unfiltered": 119216, 
    "filtered": 117056, 
    "device": "openaps://cgm", 
    "rssi": 182, 
    "type": "sgv", 
    "glucose": 112
  }, 
  {
    "trend_arrow": "FLAT", 
    "display_time": "2016-07-14T21:21:13-07:00", 
    "noise": 1, 
    "system_time": "2016-07-15T04:12:28-07:00", 
    "direction": "Flat", 
    "sgv": 113, 
    "dateString": "2016-07-14T21:21:13-07:00", 
    "date": 1468556473000, 
    "unfiltered": 119696, 
    "filtered": 115088, 
    "device": "openaps://cgm", 
    "rssi": 174, 
    "type": "sgv", 
    "glucose": 113
  }
]