[
  {
    "trend_arrow": "FLAT", 
    "display_time": "2016-06-27T13:45:10-07:00", 
    "noise": 1, 
    "system_time": "2016-06-27T19:41:55-07:00", 
    "direction": "Flat", 
    "sgv": 97, 
    "dateString": "2016-06-27T13:45:10-07:00", 
    "date": 1467060310000, 
    "unfiltered": 130384, 
    "filtered": 135200, 
    "device": "openaps://cgm", 
    "rssi": 197, 
    "type": "sgv", 
    "glucose": 97
  }, 
  {
    "trend_arrow": "FLAT", 
    "display_time": "2016-06-27T13:40:09-07:00", 
    "noise": 1, 
    "system_time": "2016-06-27T19:36:55-07:00", 
    "direction": "Flat", 
    "sgv": 100, 
    "dateString": "2016-06-27T13:40:09-07:00", 
    "date": 1467060009000, 
    "unfiltered": 133888, 
    "filtered": 138656, 
    "device": "openaps://cgm", 
    "rssi": 199, 
    "type": "sgv", 
    "glucose": 100
  }, 
  {
    "trend_arrow": "FLAT", 
    "display_time": "2016-06-27T14:10:10-07:00", 
    "noise": 1, 
    "system_time": "2016-06-27T20:06:55-07:00", 
    "direction": "Flat", 
    "sgv": 82, 
    "dateString": "2016-06-27T14:10:10-07:00", 
    "date": 1467061810000, 
    "unfiltered": 112544, 
    "filtered": 116080, 
    "device": "openaps://cgm", 
    "rssi": 471, 
    "type": "sgv", 
    "glucose": 82
  }, 
  {
    "trend_arrow": "FLAT", 
    "display_time": "2016-06-27T14:05:09-07:00", 
    "noise": 1, 
    "system_time": "2016-06-27T20:01:55-07:00", 
    "direction": "Flat", 
    "sgv": 84, 
    "dateString": "2016-06-27T14:05:09-07:00", 
    "date": 1467061509000, 
    "unfiltered": 114816, 
    "filtered": 119520, 
    "device": "openaps://cgm", 
    "rssi": 211, 
    "type": "sgv", 
    "glucose": 84
  }, 
  {
    "trend_arrow": "45_UP", 
    "display_time": "2016-06-27T15:05:10-07:00", 
    "noise": 1, 
    "system_time": "2016-06-27T21:01:55-07:00", 
    "direction": "FortyFiveUp", 
    "sgv": 109, 
    "dateString": "2016-06-27T15:05:10-07:00", 
    "date": 1467065110000, 
    "unfiltered": 144992, 
    "filtered": 133760, 
    "device": "openaps://cgm", 
    "rssi": 473, 
    "type": "sgv", 
    "glucose": 109
  }, 
  {
    "trend_arrow": "45_UP", 
    "display_time": "2016-06-27T15:00:09-07:00", 
    "noise": 1, 
    "system_time": "2016-06-27T20:56:55-07:00", 
    "direction": "FortyFiveUp", 
    "sgv": 103, 
    "dateString": "2016-06-27T15:00:09-07:00", 
    "date": 1467064809000, 
    "unfiltered": 137664, 
    "filtered": 126576, 
    "device": "openaps://cgm", 
    "rssi": 208, 
    "type": "sgv", 
    "glucose": 103
  }, 
  {
    "trend_arrow": "45_UP", 
    "display_time": "2016-06-27T15:30:10-07:00", 
    "noise": 1, 
    "system_time": "2016-06-27T21:26:55-07:00", 
    "direction": "FortyFiveUp", 
    "sgv": 138, 
    "dateString": "2016-06-27T15:30:10-07:00", 
    "date": 1467066610000, 
    "unfiltered": 181024, 
    "filtered": 169376, 
    "device": "openaps://cgm", 
    "rssi": 463, 
    "type": "sgv", 
    "glucose": 138
  }, 
  {
    "trend_arrow": "45_UP", 
    "display_time": "2016-06-27T15:25:09-07:00", 
    "noise": 1, 
    "system_time": "2016-06-27T21:21:55-07:00", 
    "direction": "FortyFiveUp", 
    "sgv": 132, 
    "dateString": "2016-06-27T15:25:09-07:00", 
    "date": 1467066309000, 
    "unfiltered": 173024, 
    "filtered": 161856, 
    "device": "openaps://cgm", 
    "rssi": 193, 
    "type": "sgv", 
    "glucose": 132
  }, 
  {
    "trend_arrow": "FLAT", 
    "display_time": "2016-06-27T15:55:09-07:00", 
    "noise": 1, 
    "system_time": "2016-06-27T21:51:54-07:00", 
    "direction": "Flat", 
    "sgv": 141, 
    "dateString": "2016-06-27T15:55:09-07:00", 
    "date": 1467068109000, 
    "unfiltered": 184832, 
    "filtered": 191328, 
    "device": "openaps://cgm", 
    "rssi": 205, 
    "type": "sgv", 
    "glucose": 141
  }, 
  {
    "trend_arrow": "FLAT", 
    "display_time": "2016-06-27T15:50:09-07:00", 
    "noise": 1, 
    "system_time": "2016-06-27T21:46:55-07:00", 
    "direction": "Flat", 
    "sgv": 145, 
    "dateString": "2016-06-27T15:50:09-07:00", 
    "date": 1467067809000, 
    "unfiltered": 190016, 
    "filtered": 191264, 
    "device": "openaps://cgm", 
    "rssi": 432, 
    "type": "sgv", 
    "glucose": 145
  }, 
  {
    "trend_arrow": "FLAT", 
    "display_time": "2016-06-27T15:45:09-07:00", 
    "noise": 1, 
    "system_time": "2016-06-27T21:41:55-07:00", 
    "direction": "Flat", 
    "sgv": 147, 
    "dateString": "2016-06-27T15:45:09-07:00", 
    "date": 1467067509000, 
    "unfiltered": 192256, 
    "filtered": 188384, 
    "device": "openaps://cgm", 
    "rssi": 213, 
    "type": "sgv", 
    "glucose": 147
  }, 
  {
    "trend_arrow": "FLAT", 
    "display_time": "2016-06-27T15:40:09-07:00", 
    "noise": 1, 
    "system_time": "2016-06-27T21:36:55-07:00", 
    "direction": "Flat", 
    "sgv": 146, 
    "dateString": "2016-06-27T15:40:09-07:00", 
    "date": 1467067209000, 
    "unfiltered": 190432, 
    "filtered": 183328, 
    "device": "openaps://cgm", 
    "rssi": 217, 
    "type": "sgv", 
    "glucose": 146
  }, 
  {
    "trend_arrow": "45_UP", 
    "display_time": "2016-06-27T15:35:09-07:00", 
    "noise": 1, 
    "system_time": "2016-06-27T21:31:55-07:00", 
    "direction": "FortyFiveUp", 
    "sgv": 142, 
    "dateString": "2016-06-27T15:35:09-07:00", 
    "date": 1467066909000, 
    "unfiltered": 186400, 
    "filtered": 176800, 
    "device": "openaps://cgm", 
    "rssi": 197, 
    "type": "sgv", 
    "glucose": 142
  }, 
  {
    "trend_arrow": "45_UP", 
    "display_time": "2016-06-27T15:30:10-07:00", 
    "noise": 1, 
    "system_time": "2016-06-27T21:26:55-07:00", 
    "direction": "FortyFiveUp", 
    "sgv": 138, 
    "dateString": "2016-06-27T15:30:10-07:00", 
    "date": 1467066610000, 
    "unfiltered": 181024, 
    "filtered": 169376, 
    "device": "openaps://cgm", 
    "rssi": 463, 
    "type": "sgv", 
    "glucose": 138
  }
]