[
  {
    "trend_arrow": "FLAT", 
    "display_time": "2016-07-04T01:02:06-07:00", 
    "noise": 1, 
    "system_time": "2016-07-04T06:58:51-07:00", 
    "direction": "Flat", 
    "sgv": 115, 
    "dateString": "2016-07-04T01:02:06-07:00", 
    "date": 1467619326000, 
    "unfiltered": 134144, 
    "filtered": 135200, 
    "device": "openaps://cgm", 
    "rssi": 441, 
    "type": "sgv", 
    "glucose": 115
  }, 
  {
    "trend_arrow": "FLAT", 
    "display_time": "2016-07-04T05:12:05-07:00", 
    "noise": 1, 
    "system_time": "2016-07-04T11:08:50-07:00", 
    "direction": "Flat", 
    "sgv": 116, 
    "dateString": "2016-07-04T05:12:05-07:00", 
    "date": 1467634325000, 
    "unfiltered": 142688, 
    "filtered": 138368, 
    "device": "openaps://cgm", 
    "rssi": 195, 
    "type": "sgv", 
    "glucose": 116
  }, 
  {
    "trend_arrow": "FLAT", 
    "display_time": "2016-07-04T05:07:04-07:00", 
    "noise": 1, 
    "system_time": "2016-07-04T11:03:50-07:00", 
    "direction": "Flat", 
    "sgv": 110, 
    "dateString": "2016-07-04T05:07:04-07:00", 
    "date": 1467634024000, 
    "unfiltered": 136832, 
    "filtered": 138432, 
    "device": "openaps://cgm", 
    "rssi": 193, 
    "type": "sgv", 
    "glucose": 110
  }, 
  {
    "trend_arrow": "45_UP", 
    "display_time": "2016-07-04T05:27:04-07:00", 
    "noise": 1, 
    "system_time": "2016-07-04T11:23:50-07:00", 
    "direction": "FortyFiveUp", 
    "sgv": 132, 
    "dateString": "2016-07-04T05:27:04-07:00", 
    "date": 1467635224000, 
    "unfiltered": 157920, 
    "filtered": 150112, 
    "device": "openaps://cgm", 
    "rssi": 197, 
    "type": "sgv", 
    "glucose": 132
  }, 
  {
    "trend_arrow": "45_UP", 
    "display_time": "2016-07-04T05:22:04-07:00", 
    "noise": 1, 
    "system_time": "2016-07-04T11:18:50-07:00", 
    "direction": "FortyFiveUp", 
    "sgv": 127, 
    "dateString": "2016-07-04T05:22:04-07:00", 
    "date": 1467634924000, 
    "unfiltered": 153344, 
    "filtered": 144320, 
    "device": "openaps://cgm", 
    "rssi": 197, 
    "type": "sgv", 
    "glucose": 127
  }
]