[
  {
    "trend_arrow": "FLAT", 
    "display_time": "2016-07-08T15:01:42-07:00", 
    "noise": 1, 
    "system_time": "2016-07-08T20:58:27-07:00", 
    "direction": "Flat", 
    "sgv": 196, 
    "dateString": "2016-07-08T15:01:42-07:00", 
    "date": 1468015302000, 
    "unfiltered": 203584, 
    "filtered": 214464, 
    "device": "openaps://cgm", 
    "rssi": 457, 
    "type": "sgv", 
    "glucose": 196
  }, 
  {
    "trend_arrow": "FLAT", 
    "display_time": "2016-07-08T14:56:41-07:00", 
    "noise": 1, 
    "system_time": "2016-07-08T20:53:27-07:00", 
    "direction": "Flat", 
    "sgv": 205, 
    "dateString": "2016-07-08T14:56:41-07:00", 
    "date": 1468015001000, 
    "unfiltered": 211840, 
    "filtered": 215424, 
    "device": "openaps://cgm", 
    "rssi": 201, 
    "type": "sgv", 
    "glucose": 205
  }, 
  {
    "trend_arrow": "FLAT", 
    "display_time": "2016-07-08T17:26:41-07:00", 
    "noise": 1, 
    "system_time": "2016-07-08T23:23:26-07:00", 
    "direction": "Flat", 
    "sgv": 138, 
    "dateString": "2016-07-08T17:26:41-07:00", 
    "date": 1468024001000, 
    "unfiltered": 152192, 
    "filtered": 152928, 
    "device": "openaps://cgm", 
    "rssi": 186, 
    "type": "sgv", 
    "glucose": 138
  }, 
  {
    "trend_arrow": "FLAT", 
    "display_time": "2016-07-08T17:21:41-07:00", 
    "noise": 1, 
    "system_time": "2016-07-08T23:18:26-07:00", 
    "direction": "Flat", 
    "sgv": 137, 
    "dateString": "2016-07-08T17:21:41-07:00", 
    "date": 1468023701000, 
    "unfiltered": 151328, 
    "filtered": 156480, 
    "device": "openaps://cgm", 
    "rssi": 207, 
    "type": "sgv", 
    "glucose": 137
  }
]