[
  {
    "trend_arrow": "FLAT", 
    "display_time": "2016-07-13T12:56:21-07:00", 
    "noise": 1, 
    "system_time": "2016-07-13T19:47:36-07:00", 
    "direction": "Flat", 
    "sgv": 79, 
    "dateString": "2016-07-13T12:56:21-07:00", 
    "date": 1468439781000, 
    "unfiltered": 90880, 
    "filtered": 86432, 
    "device": "openaps://cgm", 
    "rssi": 434, 
    "type": "sgv", 
    "glucose": 79
  }, 
  {
    "trend_arrow": "FLAT", 
    "display_time": "2016-07-13T12:51:20-07:00", 
    "noise": 1, 
    "system_time": "2016-07-13T19:42:36-07:00", 
    "direction": "Flat", 
    "sgv": 76, 
    "dateString": "2016-07-13T12:51:20-07:00", 
    "date": 1468439480000, 
    "unfiltered": 87888, 
    "filtered": 86032, 
    "device": "openaps://cgm", 
    "rssi": 171, 
    "type": "sgv", 
    "glucose": 76
  }, 
  {
    "trend_arrow": "45_UP", 
    "display_time": "2016-07-13T15:21:20-07:00", 
    "noise": 1, 
    "system_time": "2016-07-13T22:12:35-07:00", 
    "direction": "FortyFiveUp", 
    "sgv": 169, 
    "dateString": "2016-07-13T15:21:20-07:00", 
    "date": 1468448480000, 
    "unfiltered": 173472, 
    "filtered": 163072, 
    "device": "openaps://cgm", 
    "rssi": 195, 
    "type": "sgv", 
    "glucose": 169
  }, 
  {
    "trend_arrow": "FLAT", 
    "display_time": "2016-07-13T15:16:20-07:00", 
    "noise": 1, 
    "system_time": "2016-07-13T22:07:35-07:00", 
    "direction": "Flat", 
    "sgv": 160, 
    "dateString": "2016-07-13T15:16:20-07:00", 
    "date": 1468448180000, 
    "unfiltered": 165728, 
    "filtered": 157824, 
    "device": "openaps://cgm", 
    "rssi": 183, 
    "type": "sgv", 
    "glucose": 160
  }
]