[
  {
    "trend_arrow": "FLAT", 
    "display_time": "2016-07-05T09:41:58-07:00", 
    "noise": 1, 
    "direction": "Flat", 
    "system_time": "2016-07-05T15:38:44-07:00", 
    "sgv": 118, 
    "dateString": "2016-07-05T09:41:58-07:00", 
    "device": "openaps://cgm", 
    "unfiltered": 129104, 
    "rssi": 199, 
    "date": 1467736918000.0, 
    "filtered": 127392, 
    "type": "sgv", 
    "glucose": 118
  }, 
  {
    "trend_arrow": "FLAT", 
    "display_time": "2016-07-05T09:36:58-07:00", 
    "noise": 1, 
    "direction": "Flat", 
    "system_time": "2016-07-05T15:33:44-07:00", 
    "sgv": 112, 
    "dateString": "2016-07-05T09:36:58-07:00", 
    "device": "openaps://cgm", 
    "unfiltered": 125072, 
    "rssi": 198, 
    "date": 1467736618000.0, 
    "filtered": 129120, 
    "type": "sgv", 
    "glucose": 112
  }, 
  {
    "trend_arrow": "FLAT", 
    "display_time": "2016-07-05T09:31:58-07:00", 
    "noise": 1, 
    "direction": "Flat", 
    "system_time": "2016-07-05T15:28:44-07:00", 
    "sgv": 108, 
    "dateString": "2016-07-05T09:31:58-07:00", 
    "device": "openaps://cgm", 
    "unfiltered": 122208, 
    "rssi": 198, 
    "date": 1467736318000.0, 
    "filtered": 127696, 
    "type": "sgv", 
    "glucose": 108
  }, 
  {
    "trend_arrow": "45_UP", 
    "display_time": "2016-07-05T09:26:58-07:00", 
    "noise": 1, 
    "direction": "FortyFiveUp", 
    "system_time": "2016-07-05T15:23:44-07:00", 
    "sgv": 120, 
    "dateString": "2016-07-05T09:26:58-07:00", 
    "device": "openaps://cgm", 
    "unfiltered": 130768, 
    "rssi": 198, 
    "date": 1467736018000.0, 
    "filtered": 121328, 
    "type": "sgv", 
    "glucose": 120
  }, 
  {
    "trend_arrow": "SINGLE_UP", 
    "display_time": "2016-07-05T09:21:58-07:00", 
    "noise": 1, 
    "direction": "SingleUp", 
    "system_time": "2016-07-05T15:18:44-07:00", 
    "sgv": 114, 
    "dateString": "2016-07-05T09:21:58-07:00", 
    "device": "openaps://cgm", 
    "unfiltered": 126608, 
    "rssi": 184, 
    "date": 1467735718000.0, 
    "filtered": 112448, 
    "type": "sgv", 
    "glucose": 114
  }, 
  {
    "trend_arrow": "45_UP", 
    "display_time": "2016-07-05T09:16:58-07:00", 
    "noise": 1, 
    "direction": "FortyFiveUp", 
    "system_time": "2016-07-05T15:13:44-07:00", 
    "sgv": 107, 
    "dateString": "2016-07-05T09:16:58-07:00", 
    "device": "openaps://cgm", 
    "unfiltered": 120960, 
    "rssi": 196, 
    "date": 1467735418000.0, 
    "filtered": 104944, 
    "type": "sgv", 
    "glucose": 107
  }, 
  {
    "trend_arrow": "FLAT", 
    "display_time": "2016-07-05T09:11:58-07:00", 
    "noise": 1, 
    "direction": "Flat", 
    "system_time": "2016-07-05T15:08:44-07:00", 
    "sgv": 89, 
    "dateString": "2016-07-05T09:11:58-07:00", 
    "device": "openaps://cgm", 
    "unfiltered": 107840, 
    "rssi": 196, 
    "date": 1467735118000.0, 
    "filtered": 100512, 
    "type": "sgv", 
    "glucose": 89
  }, 
  {
    "trend_arrow": "FLAT", 
    "display_time": "2016-07-05T09:06:58-07:00", 
    "noise": 1, 
    "direction": "Flat", 
    "system_time": "2016-07-05T15:03:44-07:00", 
    "sgv": 81, 
    "dateString": "2016-07-05T09:06:58-07:00", 
    "device": "openaps://cgm", 
    "unfiltered": 102048, 
    "rssi": 196, 
    "date": 1467734818000.0, 
    "filtered": 98640, 
    "type": "sgv", 
    "glucose": 81
  }, 
  {
    "trend_arrow": "FLAT", 
    "display_time": "2016-07-05T09:01:58-07:00", 
    "noise": 1, 
    "direction": "Flat", 
    "system_time": "2016-07-05T14:58:44-07:00", 
    "sgv": 76, 
    "dateString": "2016-07-05T09:01:58-07:00", 
    "device": "openaps://cgm", 
    "unfiltered": 98352, 
    "rssi": 196, 
    "date": 1467734518000.0, 
    "filtered": 97456, 
    "type": "sgv", 
    "glucose": 76
  }, 
  {
    "trend_arrow": "FLAT", 
    "display_time": "2016-07-05T08:56:58-07:00", 
    "noise": 1, 
    "direction": "Flat", 
    "system_time": "2016-07-05T14:53:44-07:00", 
    "sgv": 74, 
    "dateString": "2016-07-05T08:56:58-07:00", 
    "device": "openaps://cgm", 
    "unfiltered": 97008, 
    "rssi": 196, 
    "date": 1467734218000.0, 
    "filtered": 96352, 
    "type": "sgv", 
    "glucose": 74
  }, 
  {
    "trend_arrow": "FLAT", 
    "display_time": "2016-07-05T08:51:58-07:00", 
    "noise": 1, 
    "direction": "Flat", 
    "system_time": "2016-07-05T14:48:44-07:00", 
    "sgv": 77, 
    "dateString": "2016-07-05T08:51:58-07:00", 
    "device": "openaps://cgm", 
    "unfiltered": 99360, 
    "rssi": 198, 
    "date": 1467733918000.0, 
    "filtered": 94832, 
    "type": "sgv", 
    "glucose": 77
  }, 
  {
    "trend_arrow": "FLAT", 
    "display_time": "2016-07-05T08:46:58-07:00", 
    "noise": 1, 
    "direction": "Flat", 
    "system_time": "2016-07-05T14:43:44-07:00", 
    "sgv": 68, 
    "dateString": "2016-07-05T08:46:58-07:00", 
    "device": "openaps://cgm", 
    "unfiltered": 92704, 
    "rssi": 199, 
    "date": 1467733618000.0, 
    "filtered": 93568, 
    "type": "sgv", 
    "glucose": 68
  }, 
  {
    "trend_arrow": "FLAT", 
    "display_time": "2016-07-05T08:41:59-07:00", 
    "noise": 1, 
    "direction": "Flat", 
    "system_time": "2016-07-05T14:38:44-07:00", 
    "sgv": 74, 
    "dateString": "2016-07-05T08:41:59-07:00", 
    "device": "openaps://cgm", 
    "unfiltered": 97008, 
    "rssi": 451, 
    "date": 1467733319000.0, 
    "filtered": 93568, 
    "type": "sgv", 
    "glucose": 74
  }, 
  {
    "trend_arrow": "FLAT", 
    "display_time": "2016-07-05T08:37:00-07:00", 
    "noise": 1, 
    "direction": "Flat", 
    "system_time": "2016-07-05T14:33:45-07:00", 
    "sgv": 70, 
    "dateString": "2016-07-05T08:37:00-07:00", 
    "device": "openaps://cgm", 
    "unfiltered": 94224, 
    "rssi": 193, 
    "date": 1467733020000.0, 
    "filtered": 94608, 
    "type": "sgv", 
    "glucose": 70
  }, 
  {
    "trend_arrow": "FLAT", 
    "display_time": "2016-07-05T08:36:59-07:00", 
    "noise": 1, 
    "direction": "Flat", 
    "system_time": "2016-07-05T14:33:45-07:00", 
    "sgv": 71, 
    "dateString": "2016-07-05T08:36:59-07:00", 
    "device": "openaps://cgm", 
    "unfiltered": 90736, 
    "rssi": 169, 
    "date": 1467733019000.0, 
    "filtered": 96544, 
    "type": "sgv", 
    "glucose": 71
  }, 
  {
    "trend_arrow": "FLAT", 
    "display_time": "2016-07-05T08:31:58-07:00", 
    "noise": 1, 
    "direction": "Flat", 
    "system_time": "2016-07-05T14:28:44-07:00", 
    "sgv": 66, 
    "dateString": "2016-07-05T08:31:58-07:00", 
    "device": "openaps://cgm", 
    "unfiltered": 96848, 
    "rssi": 197, 
    "date": 1467732718000.0, 
    "filtered": 98464, 
    "type": "sgv", 
    "glucose": 66
  }, 
  {
    "trend_arrow": "FLAT", 
    "display_time": "2016-07-05T08:26:59-07:00", 
    "noise": 1, 
    "direction": "Flat", 
    "system_time": "2016-07-05T14:23:44-07:00", 
    "sgv": 74, 
    "dateString": "2016-07-05T08:26:59-07:00", 
    "device": "openaps://cgm", 
    "unfiltered": 97520, 
    "rssi": 197, 
    "date": 1467732419000.0, 
    "filtered": 100368, 
    "type": "sgv", 
    "glucose": 74
  }, 
  {
    "trend_arrow": "FLAT", 
    "display_time": "2016-07-05T08:21:58-07:00", 
    "noise": 1, 
    "direction": "Flat", 
    "system_time": "2016-07-05T14:18:44-07:00", 
    "sgv": 75, 
    "dateString": "2016-07-05T08:21:58-07:00", 
    "device": "openaps://cgm", 
    "unfiltered": 99216, 
    "rssi": 197, 
    "date": 1467732118000.0, 
    "filtered": 103056, 
    "type": "sgv", 
    "glucose": 75
  }, 
  {
    "trend_arrow": "FLAT", 
    "display_time": "2016-07-05T08:16:59-07:00", 
    "noise": 1, 
    "direction": "Flat", 
    "system_time": "2016-07-05T14:13:44-07:00", 
    "sgv": 77, 
    "dateString": "2016-07-05T08:16:59-07:00", 
    "device": "openaps://cgm", 
    "unfiltered": 102368, 
    "rssi": 197, 
    "date": 1467731819000.0, 
    "filtered": 106512, 
    "type": "sgv", 
    "glucose": 77
  }, 
  {
    "trend_arrow": "FLAT", 
    "display_time": "2016-07-05T08:11:59-07:00", 
    "noise": 1, 
    "direction": "Flat", 
    "system_time": "2016-07-05T14:08:44-07:00", 
    "sgv": 81, 
    "dateString": "2016-07-05T08:11:59-07:00", 
    "device": "openaps://cgm", 
    "unfiltered": 104160, 
    "rssi": 198, 
    "date": 1467731519000.0, 
    "filtered": 110144, 
    "type": "sgv", 
    "glucose": 81
  }, 
  {
    "trend_arrow": "FLAT", 
    "display_time": "2016-07-05T08:06:59-07:00", 
    "noise": 1, 
    "direction": "Flat", 
    "system_time": "2016-07-05T14:03:44-07:00", 
    "sgv": 84, 
    "dateString": "2016-07-05T08:06:59-07:00", 
    "device": "openaps://cgm", 
    "unfiltered": 107168, 
    "rssi": 198, 
    "date": 1467731219000.0, 
    "filtered": 112656, 
    "type": "sgv", 
    "glucose": 84
  }, 
  {
    "trend_arrow": "FLAT", 
    "display_time": "2016-07-05T08:01:59-07:00", 
    "noise": 1, 
    "direction": "Flat", 
    "system_time": "2016-07-05T13:58:44-07:00", 
    "sgv": 88, 
    "dateString": "2016-07-05T08:01:59-07:00", 
    "device": "openaps://cgm", 
    "unfiltered": 110304, 
    "rssi": 198, 
    "date": 1467730919000.0, 
    "filtered": 113664, 
    "type": "sgv", 
    "glucose": 88
  }, 
  {
    "trend_arrow": "FLAT", 
    "display_time": "2016-07-05T07:56:59-07:00", 
    "noise": 1, 
    "direction": "Flat", 
    "system_time": "2016-07-05T13:53:44-07:00", 
    "sgv": 92, 
    "dateString": "2016-07-05T07:56:59-07:00", 
    "device": "openaps://cgm", 
    "unfiltered": 114768, 
    "rssi": 198, 
    "date": 1467730619000.0, 
    "filtered": 115088, 
    "type": "sgv", 
    "glucose": 92
  }, 
  {
    "trend_arrow": "FLAT", 
    "display_time": "2016-07-05T07:51:59-07:00", 
    "noise": 1, 
    "direction": "Flat", 
    "system_time": "2016-07-05T13:48:44-07:00", 
    "sgv": 98, 
    "dateString": "2016-07-05T07:51:59-07:00", 
    "device": "openaps://cgm", 
    "unfiltered": 118256, 
    "rssi": 198, 
    "date": 1467730319000.0, 
    "filtered": 118576, 
    "type": "sgv", 
    "glucose": 98
  }, 
  {
    "trend_arrow": "FLAT", 
    "display_time": "2016-07-05T07:46:59-07:00", 
    "noise": 1, 
    "direction": "Flat", 
    "system_time": "2016-07-05T13:43:44-07:00", 
    "sgv": 103, 
    "dateString": "2016-07-05T07:46:59-07:00", 
    "device": "openaps://cgm", 
    "unfiltered": 112960, 
    "rssi": 196, 
    "date": 1467730019000.0, 
    "filtered": 124336, 
    "type": "sgv", 
    "glucose": 103
  }, 
  {
    "trend_arrow": "45_DOWN", 
    "display_time": "2016-07-05T07:41:59-07:00", 
    "noise": 1, 
    "direction": "FortyFiveDown", 
    "system_time": "2016-07-05T13:38:44-07:00", 
    "sgv": 96, 
    "dateString": "2016-07-05T07:41:59-07:00", 
    "device": "openaps://cgm", 
    "unfiltered": 120736, 
    "rssi": 196, 
    "date": 1467729719000.0, 
    "filtered": 130944, 
    "type": "sgv", 
    "glucose": 96
  }, 
  {
    "trend_arrow": "45_DOWN", 
    "display_time": "2016-07-05T07:36:59-07:00", 
    "noise": 1, 
    "direction": "FortyFiveDown", 
    "system_time": "2016-07-05T13:33:44-07:00", 
    "sgv": 106, 
    "dateString": "2016-07-05T07:36:59-07:00", 
    "device": "openaps://cgm", 
    "unfiltered": 127744, 
    "rssi": 186, 
    "date": 1467729419000.0, 
    "filtered": 136352, 
    "type": "sgv", 
    "glucose": 106
  }, 
  {
    "trend_arrow": "45_DOWN", 
    "display_time": "2016-07-05T07:31:59-07:00", 
    "noise": 1, 
    "direction": "FortyFiveDown", 
    "system_time": "2016-07-05T13:28:44-07:00", 
    "sgv": 116, 
    "dateString": "2016-07-05T07:31:59-07:00", 
    "device": "openaps://cgm", 
    "unfiltered": 132448, 
    "rssi": 185, 
    "date": 1467729119000.0, 
    "filtered": 139808, 
    "type": "sgv", 
    "glucose": 116
  }, 
  {
    "trend_arrow": "FLAT", 
    "display_time": "2016-07-05T07:26:59-07:00", 
    "noise": 1, 
    "direction": "Flat", 
    "system_time": "2016-07-05T13:23:44-07:00", 
    "sgv": 122, 
    "dateString": "2016-07-05T07:26:59-07:00", 
    "device": "openaps://cgm", 
    "unfiltered": 137760, 
    "rssi": 185, 
    "date": 1467728819000.0, 
    "filtered": 141408, 
    "type": "sgv", 
    "glucose": 122
  }, 
  {
    "trend_arrow": "FLAT", 
    "display_time": "2016-07-05T07:21:59-07:00", 
    "noise": 1, 
    "direction": "Flat", 
    "system_time": "2016-07-05T13:18:44-07:00", 
    "sgv": 129, 
    "dateString": "2016-07-05T07:21:59-07:00", 
    "device": "openaps://cgm", 
    "unfiltered": 142688, 
    "rssi": 187, 
    "date": 1467728519000.0, 
    "filtered": 142112, 
    "type": "sgv", 
    "glucose": 129
  }, 
  {
    "trend_arrow": "FLAT", 
    "display_time": "2016-07-05T07:16:59-07:00", 
    "noise": 1, 
    "direction": "Flat", 
    "system_time": "2016-07-05T13:13:44-07:00", 
    "sgv": 136, 
    "dateString": "2016-07-05T07:16:59-07:00", 
    "device": "openaps://cgm", 
    "unfiltered": 141920, 
    "rssi": 194, 
    "date": 1467728219000.0, 
    "filtered": 143616, 
    "type": "sgv", 
    "glucose": 136
  }, 
  {
    "trend_arrow": "FLAT", 
    "display_time": "2016-07-05T07:11:59-07:00", 
    "noise": 1, 
    "direction": "Flat", 
    "system_time": "2016-07-05T13:08:44-07:00", 
    "sgv": 135, 
    "dateString": "2016-07-05T07:11:59-07:00", 
    "device": "openaps://cgm", 
    "unfiltered": 143616, 
    "rssi": 195, 
    "date": 1467727919000.0, 
    "filtered": 146496, 
    "type": "sgv", 
    "glucose": 135
  }, 
  {
    "trend_arrow": "FLAT", 
    "display_time": "2016-07-05T07:06:59-07:00", 
    "noise": 1, 
    "direction": "Flat", 
    "system_time": "2016-07-05T13:03:44-07:00", 
    "sgv": 137, 
    "dateString": "2016-07-05T07:06:59-07:00", 
    "device": "openaps://cgm", 
    "unfiltered": 144000, 
    "rssi": 193, 
    "date": 1467727619000.0, 
    "filtered": 149728, 
    "type": "sgv", 
    "glucose": 137
  }, 
  {
    "trend_arrow": "FLAT", 
    "display_time": "2016-07-05T07:01:59-07:00", 
    "noise": 1, 
    "direction": "Flat", 
    "system_time": "2016-07-05T12:58:44-07:00", 
    "sgv": 138, 
    "dateString": "2016-07-05T07:01:59-07:00", 
    "device": "openaps://cgm", 
    "unfiltered": 147136, 
    "rssi": 705, 
    "date": 1467727319000.0, 
    "filtered": 151136, 
    "type": "sgv", 
    "glucose": 138
  }, 
  {
    "trend_arrow": "FLAT", 
    "display_time": "2016-07-05T06:57:00-07:00", 
    "noise": 1, 
    "direction": "Flat", 
    "system_time": "2016-07-05T12:53:45-07:00", 
    "sgv": 142, 
    "dateString": "2016-07-05T06:57:00-07:00", 
    "device": "openaps://cgm", 
    "unfiltered": 147936, 
    "rssi": 195, 
    "date": 1467727020000.0, 
    "filtered": 149504, 
    "type": "sgv", 
    "glucose": 142
  }, 
  {
    "trend_arrow": "FLAT", 
    "display_time": "2016-07-05T06:51:59-07:00", 
    "noise": 1, 
    "direction": "Flat", 
    "system_time": "2016-07-05T12:48:44-07:00", 
    "sgv": 143, 
    "dateString": "2016-07-05T06:51:59-07:00", 
    "device": "openaps://cgm", 
    "unfiltered": 153856, 
    "rssi": 190, 
    "date": 1467726719000.0, 
    "filtered": 145632, 
    "type": "sgv", 
    "glucose": 143
  }, 
  {
    "trend_arrow": "45_UP", 
    "display_time": "2016-07-05T06:46:59-07:00", 
    "noise": 1, 
    "direction": "FortyFiveUp", 
    "system_time": "2016-07-05T12:43:44-07:00", 
    "sgv": 151, 
    "dateString": "2016-07-05T06:46:59-07:00", 
    "device": "openaps://cgm", 
    "unfiltered": 148736, 
    "rssi": 188, 
    "date": 1467726419000.0, 
    "filtered": 141248, 
    "type": "sgv", 
    "glucose": 151
  }, 
  {
    "trend_arrow": "45_UP", 
    "display_time": "2016-07-05T06:41:59-07:00", 
    "noise": 1, 
    "direction": "FortyFiveUp", 
    "system_time": "2016-07-05T12:38:44-07:00", 
    "sgv": 144, 
    "dateString": "2016-07-05T06:41:59-07:00", 
    "device": "openaps://cgm", 
    "unfiltered": 143872, 
    "rssi": 188, 
    "date": 1467726119000.0, 
    "filtered": 137152, 
    "type": "sgv", 
    "glucose": 144
  }, 
  {
    "trend_arrow": "45_UP", 
    "display_time": "2016-07-05T06:36:59-07:00", 
    "noise": 1, 
    "direction": "FortyFiveUp", 
    "system_time": "2016-07-05T12:33:44-07:00", 
    "sgv": 138, 
    "dateString": "2016-07-05T06:36:59-07:00", 
    "device": "openaps://cgm", 
    "unfiltered": 138240, 
    "rssi": 188, 
    "date": 1467725819000.0, 
    "filtered": 131776, 
    "type": "sgv", 
    "glucose": 138
  }, 
  {
    "trend_arrow": "45_UP", 
    "display_time": "2016-07-05T06:31:59-07:00", 
    "noise": 1, 
    "direction": "FortyFiveUp", 
    "system_time": "2016-07-05T12:28:44-07:00", 
    "sgv": 130, 
    "dateString": "2016-07-05T06:31:59-07:00", 
    "device": "openaps://cgm", 
    "unfiltered": 132768, 
    "rssi": 189, 
    "date": 1467725519000.0, 
    "filtered": 123632, 
    "type": "sgv", 
    "glucose": 130
  }, 
  {
    "trend_arrow": "45_UP", 
    "display_time": "2016-07-05T06:26:59-07:00", 
    "noise": 1, 
    "direction": "FortyFiveUp", 
    "system_time": "2016-07-05T12:23:45-07:00", 
    "sgv": 123, 
    "dateString": "2016-07-05T06:26:59-07:00", 
    "device": "openaps://cgm", 
    "unfiltered": 128528, 
    "rssi": 448, 
    "date": 1467725219000.0, 
    "filtered": 113888, 
    "type": "sgv", 
    "glucose": 123
  }, 
  {
    "trend_arrow": "SINGLE_UP", 
    "display_time": "2016-07-05T06:21:59-07:00", 
    "noise": 1, 
    "direction": "SingleUp", 
    "system_time": "2016-07-05T12:18:45-07:00", 
    "sgv": 117, 
    "dateString": "2016-07-05T06:21:59-07:00", 
    "device": "openaps://cgm", 
    "unfiltered": 123584, 
    "rssi": 189, 
    "date": 1467724919000.0, 
    "filtered": 105584, 
    "type": "sgv", 
    "glucose": 117
  }, 
  {
    "trend_arrow": "45_UP", 
    "display_time": "2016-07-05T06:16:59-07:00", 
    "noise": 1, 
    "direction": "FortyFiveUp", 
    "system_time": "2016-07-05T12:13:44-07:00", 
    "sgv": 110, 
    "dateString": "2016-07-05T06:16:59-07:00", 
    "device": "openaps://cgm", 
    "unfiltered": 109488, 
    "rssi": 195, 
    "date": 1467724619000.0, 
    "filtered": 102048, 
    "type": "sgv", 
    "glucose": 110
  }, 
  {
    "trend_arrow": "FLAT", 
    "display_time": "2016-07-05T06:12:00-07:00", 
    "noise": 1, 
    "direction": "Flat", 
    "system_time": "2016-07-05T12:08:45-07:00", 
    "sgv": 91, 
    "dateString": "2016-07-05T06:12:00-07:00", 
    "device": "openaps://cgm", 
    "unfiltered": 104640, 
    "rssi": 455, 
    "date": 1467724320000.0, 
    "filtered": 103856, 
    "type": "sgv", 
    "glucose": 91
  }, 
  {
    "trend_arrow": "FLAT", 
    "display_time": "2016-07-05T06:11:59-07:00", 
    "noise": 1, 
    "direction": "Flat", 
    "system_time": "2016-07-05T12:08:45-07:00", 
    "sgv": 95, 
    "dateString": "2016-07-05T06:11:59-07:00", 
    "device": "openaps://cgm", 
    "unfiltered": 100176, 
    "rssi": 185, 
    "date": 1467724319000.0, 
    "filtered": 108416, 
    "type": "sgv", 
    "glucose": 95
  }, 
  {
    "trend_arrow": "FLAT", 
    "display_time": "2016-07-05T06:06:59-07:00", 
    "noise": 1, 
    "direction": "Flat", 
    "system_time": "2016-07-05T12:03:45-07:00", 
    "sgv": 83, 
    "dateString": "2016-07-05T06:06:59-07:00", 
    "device": "openaps://cgm", 
    "unfiltered": 102544, 
    "rssi": 185, 
    "date": 1467724019000.0, 
    "filtered": 113696, 
    "type": "sgv", 
    "glucose": 83
  }, 
  {
    "trend_arrow": "45_DOWN", 
    "display_time": "2016-07-05T06:01:59-07:00", 
    "noise": 1, 
    "direction": "FortyFiveDown", 
    "system_time": "2016-07-05T11:58:44-07:00", 
    "sgv": 77, 
    "dateString": "2016-07-05T06:01:59-07:00", 
    "device": "openaps://cgm", 
    "unfiltered": 113712, 
    "rssi": 184, 
    "date": 1467723719000.0, 
    "filtered": 118384, 
    "type": "sgv", 
    "glucose": 77
  }, 
  {
    "trend_arrow": "45_DOWN", 
    "display_time": "2016-07-05T05:56:59-07:00", 
    "noise": 1, 
    "direction": "FortyFiveDown", 
    "system_time": "2016-07-05T11:53:45-07:00", 
    "sgv": 80, 
    "dateString": "2016-07-05T05:56:59-07:00", 
    "device": "openaps://cgm", 
    "unfiltered": 115776, 
    "rssi": 447, 
    "date": 1467723419000.0, 
    "filtered": 121840, 
    "type": "sgv", 
    "glucose": 80
  }, 
  {
    "trend_arrow": "FLAT", 
    "display_time": "2016-07-05T05:51:59-07:00", 
    "noise": 1, 
    "direction": "Flat", 
    "system_time": "2016-07-05T11:48:45-07:00", 
    "sgv": 95, 
    "dateString": "2016-07-05T05:51:59-07:00", 
    "device": "openaps://cgm", 
    "unfiltered": 118256, 
    "rssi": 191, 
    "date": 1467723119000.0, 
    "filtered": 122912, 
    "type": "sgv", 
    "glucose": 95
  }, 
  {
    "trend_arrow": "FLAT", 
    "display_time": "2016-07-05T05:47:00-07:00", 
    "noise": 1, 
    "direction": "Flat", 
    "system_time": "2016-07-05T11:43:45-07:00", 
    "sgv": 98, 
    "dateString": "2016-07-05T05:47:00-07:00", 
    "device": "openaps://cgm", 
    "unfiltered": 121392, 
    "rssi": 183, 
    "date": 1467722820000.0, 
    "filtered": 120656, 
    "type": "sgv", 
    "glucose": 98
  }, 
  {
    "trend_arrow": "FLAT", 
    "display_time": "2016-07-05T05:41:59-07:00", 
    "noise": 1, 
    "direction": "Flat", 
    "system_time": "2016-07-05T11:38:45-07:00", 
    "sgv": 102, 
    "dateString": "2016-07-05T05:41:59-07:00", 
    "device": "openaps://cgm", 
    "unfiltered": 123024, 
    "rssi": 191, 
    "date": 1467722519000.0, 
    "filtered": 117792, 
    "type": "sgv", 
    "glucose": 102
  }, 
  {
    "trend_arrow": "FLAT", 
    "display_time": "2016-07-05T05:36:59-07:00", 
    "noise": 1, 
    "direction": "Flat", 
    "system_time": "2016-07-05T11:33:45-07:00", 
    "sgv": 106, 
    "dateString": "2016-07-05T05:36:59-07:00", 
    "device": "openaps://cgm", 
    "unfiltered": 125664, 
    "rssi": 191, 
    "date": 1467722219000.0, 
    "filtered": 118176, 
    "type": "sgv", 
    "glucose": 106
  }, 
  {
    "trend_arrow": "FLAT", 
    "display_time": "2016-07-05T05:31:59-07:00", 
    "noise": 1, 
    "direction": "Flat", 
    "system_time": "2016-07-05T11:28:45-07:00", 
    "sgv": 108, 
    "dateString": "2016-07-05T05:31:59-07:00", 
    "device": "openaps://cgm", 
    "unfiltered": 116240, 
    "rssi": 191, 
    "date": 1467721919000.0, 
    "filtered": 122976, 
    "type": "sgv", 
    "glucose": 108
  }, 
  {
    "trend_arrow": "FLAT", 
    "display_time": "2016-07-05T05:26:59-07:00", 
    "noise": 1, 
    "direction": "Flat", 
    "system_time": "2016-07-05T11:23:45-07:00", 
    "sgv": 112, 
    "dateString": "2016-07-05T05:26:59-07:00", 
    "device": "openaps://cgm", 
    "unfiltered": 116416, 
    "rssi": 196, 
    "date": 1467721619000.0, 
    "filtered": 129584, 
    "type": "sgv", 
    "glucose": 112
  }, 
  {
    "trend_arrow": "45_DOWN", 
    "display_time": "2016-07-05T05:21:59-07:00", 
    "noise": 1, 
    "direction": "FortyFiveDown", 
    "system_time": "2016-07-05T11:18:45-07:00", 
    "sgv": 99, 
    "dateString": "2016-07-05T05:21:59-07:00", 
    "device": "openaps://cgm", 
    "date": 1467721319000.0, 
    "type": "sgv", 
    "glucose": 99
  }, 
  {
    "trend_arrow": "45_DOWN", 
    "display_time": "2016-07-05T05:16:59-07:00", 
    "noise": 1, 
    "direction": "FortyFiveDown", 
    "system_time": "2016-07-05T11:13:45-07:00", 
    "sgv": 99, 
    "dateString": "2016-07-05T05:16:59-07:00", 
    "device": "openaps://cgm", 
    "date": 1467721019000.0, 
    "type": "sgv", 
    "glucose": 99
  }
]